easycheml/__init__.py
easycheml/modelling.py
easycheml/postprocessing.py
easycheml/preprocessing.py
easycheml-0.2.3.dist-info/METADATA
easycheml-0.2.3.dist-info/WHEEL
easycheml-0.2.3.dist-info/top_level.txt
easycheml-0.2.3.dist-info/RECORD
