Metadata-Version: 2.1
Name: easycheml
Version: 0.2.3
Summary: A simple tool for using artificial intelligence in chemistry
Home-page: https://github.com/anandsahuofficial/easycheml.git
Author: Anand Sahu
Author-email: anandsahuofficial@gmail.com
License: UNKNOWN
Download-URL: https://github.com/anandsahuofficial/easycheml/archive/refs/tags/easycheml.tar.gz
Platform: UNKNOWN
Classifier: Programming Language :: Python :: 3
Classifier: License :: OSI Approved :: MIT License
Classifier: Operating System :: OS Independent
Requires-Dist: Keras-Preprocessing (==1.1.2)
Requires-Dist: XlsxWriter (==3.1.2)
Requires-Dist: ipykernel (==6.16.2)
Requires-Dist: keras-tuner (==1.1.3)
Requires-Dist: keras (==2.10.0)
Requires-Dist: latex (==0.7.0)
Requires-Dist: matplotlib-inline (==0.1.6)
Requires-Dist: matplotlib (==3.6.2)
Requires-Dist: mlxtend (==0.21.0)
Requires-Dist: numba (==0.56.4)
Requires-Dist: number-recognition (==1.0.5)
Requires-Dist: numpy (==1.24.4)
Requires-Dist: openpyxl (==3.1.2)
Requires-Dist: pandas (==1.5.1)
Requires-Dist: pandocfilters (==1.5.0)
Requires-Dist: scikit-learn (==1.3.2)
Requires-Dist: scipy (==1.10.1)
Requires-Dist: scp (==0.14.4)
Requires-Dist: seaborn (==0.13.2)
Requires-Dist: statsmodels (==0.13.5)
Requires-Dist: sympy (==1.12)
Requires-Dist: tensorboard (==2.10.1)
Requires-Dist: tensorflow-estimator (==2.4.0)
Requires-Dist: tensorflow-gpu (==2.10.0)
Requires-Dist: tensorflow-io-gcs-filesystem (==0.27.0)
Requires-Dist: tqdm (==4.66.4)
Requires-Dist: xgboost (==1.7.1)
Requires-Dist: xlrd (==2.0.1)
